hopsfacets/version.py
hopsfacets-0.0.4.dist-info/DESCRIPTION.rst
hopsfacets-0.0.4.dist-info/METADATA
hopsfacets-0.0.4.dist-info/RECORD
hopsfacets-0.0.4.dist-info/WHEEL
hopsfacets-0.0.4.dist-info/metadata.json
hopsfacets-0.0.4.dist-info/top_level.txt
