Metadata-Version: 2.0
Name: hopsfacets
Version: 0.0.4
Summary: PyPi Facets for Jupyter Notebook
Home-page: https://github.com/hopshadoop/facets
Author: Google Inc., Logical Clocks AB
Author-email: jim@logicalclocks.com
License: Apache 2.0
Download-URL: http://snurran.sics.se/hops/hops-util-py/hopsfacets-0.0.4.tar.gz
Keywords: jupyter deep learning big data visualization wrangling
Platform: UNKNOWN
Classifier: Development Status :: 4 - Beta
Classifier: Intended Audience :: Developers
Classifier: Programming Language :: Python :: 2
Classifier: Programming Language :: Python :: 2.7
Requires-Dist: jupyter
Requires-Dist: numpy
Requires-Dist: pandas
Requires-Dist: protobuf
